{
  "Parameters": {
    "DynamoDBModelTableReadIOPS": {
      "Type": "Number",
      "Default": 5,
      "Description": "The number of read IOPS the table should support."
    },
    "DynamoDBModelTableWriteIOPS": {
      "Type": "Number",
      "Default": 5,
      "Description": "The number of write IOPS the table should support."
    },
    "DynamoDBBillingMode": {
      "Type": "String",
      "Default": "PAY_PER_REQUEST",
      "AllowedValues": [
        "PAY_PER_REQUEST",
        "PROVISIONED"
      ],
      "Description": "Configure @model types to create DynamoDB tables with PAY_PER_REQUEST or PROVISIONED billing modes."
    },
    "DynamoDBEnablePointInTimeRecovery": {
      "Type": "String",
      "Default": "false",
      "AllowedValues": [
        "true",
        "false"
      ],
      "Description": "Whether to enable Point in Time Recovery on the table."
    },
    "DynamoDBEnableServerSideEncryption": {
      "Type": "String",
      "Default": "true",
      "AllowedValues": [
        "true",
        "false"
      ],
      "Description": "Enable server side encryption powered by KMS."
    },
    "referencetotransformerrootstackenv10C5A902Ref": {
      "Type": "String"
    },
    "referencetotransformerrootstackGraphQLAPI20497F53ApiId": {
      "Type": "String"
    },
    "referencetotransformerrootstackGraphQLAPINONEDS2BA9D1C8Name": {
      "Type": "String"
    },
    "referencetotransformerrootstackS3DeploymentBucket7592718ARef": {
      "Type": "String"
    },
    "referencetotransformerrootstackS3DeploymentRootKeyA71EA735Ref": {
      "Type": "String"
    }
  },
  "Conditions": {
    "HasEnvironmentParameter": {
      "Fn::Not": [
        {
          "Fn::Equals": [
            {
              "Ref": "referencetotransformerrootstackenv10C5A902Ref"
            },
            "NONE"
          ]
        }
      ]
    },
    "ShouldUseServerSideEncryption": {
      "Fn::Equals": [
        {
          "Ref": "DynamoDBEnableServerSideEncryption"
        },
        "true"
      ]
    },
    "ShouldUsePayPerRequestBilling": {
      "Fn::Equals": [
        {
          "Ref": "DynamoDBBillingMode"
        },
        "PAY_PER_REQUEST"
      ]
    },
    "ShouldUsePointInTimeRecovery": {
      "Fn::Equals": [
        {
          "Ref": "DynamoDBEnablePointInTimeRecovery"
        },
        "true"
      ]
    }
  },
  "Resources": {
    "WorkflowTable": {
      "Type": "AWS::DynamoDB::Table",
      "Properties": {
        "KeySchema": [
          {
            "AttributeName": "workflowName",
            "KeyType": "HASH"
          }
        ],
        "AttributeDefinitions": [
          {
            "AttributeName": "workflowName",
            "AttributeType": "S"
          }
        ],
        "BillingMode": {
          "Fn::If": [
            "ShouldUsePayPerRequestBilling",
            "PAY_PER_REQUEST",
            {
              "Ref": "AWS::NoValue"
            }
          ]
        },
        "PointInTimeRecoverySpecification": {
          "Fn::If": [
            "ShouldUsePointInTimeRecovery",
            {
              "PointInTimeRecoveryEnabled": true
            },
            {
              "Ref": "AWS::NoValue"
            }
          ]
        },
        "ProvisionedThroughput": {
          "Fn::If": [
            "ShouldUsePayPerRequestBilling",
            {
              "Ref": "AWS::NoValue"
            },
            {
              "ReadCapacityUnits": {
                "Ref": "DynamoDBModelTableReadIOPS"
              },
              "WriteCapacityUnits": {
                "Ref": "DynamoDBModelTableWriteIOPS"
              }
            }
          ]
        },
        "SSESpecification": {
          "SSEEnabled": {
            "Fn::If": [
              "ShouldUseServerSideEncryption",
              true,
              false
            ]
          }
        },
        "StreamSpecification": {
          "StreamViewType": "NEW_AND_OLD_IMAGES"
        },
        "TableName": {
          "Fn::Join": [
            "",
            [
              "Workflow-",
              {
                "Ref": "referencetotransformerrootstackGraphQLAPI20497F53ApiId"
              },
              "-",
              {
                "Ref": "referencetotransformerrootstackenv10C5A902Ref"
              }
            ]
          ]
        }
      },
      "UpdateReplacePolicy": "Delete",
      "DeletionPolicy": "Delete"
    },
    "WorkflowIAMRole52A6C30C": {
      "Type": "AWS::IAM::Role",
      "Properties": {
        "AssumeRolePolicyDocument": {
          "Statement": [
            {
              "Action": "sts:AssumeRole",
              "Effect": "Allow",
              "Principal": {
                "Service": "appsync.amazonaws.com"
              }
            }
          ],
          "Version": "2012-10-17"
        },
        "RoleName": {
          "Fn::Join": [
            "",
            [
              "WorkflowIAMRole5b6e19-",
              {
                "Ref": "referencetotransformerrootstackGraphQLAPI20497F53ApiId"
              },
              "-",
              {
                "Ref": "referencetotransformerrootstackenv10C5A902Ref"
              }
            ]
          ]
        }
      }
    },
    "WorkflowIAMRoleDefaultPolicy4E30035E": {
      "Type": "AWS::IAM::Policy",
      "Properties": {
        "PolicyDocument": {
          "Statement": [
            {
              "Action": [
                "dynamodb:BatchGetItem",
                "dynamodb:GetRecords",
                "dynamodb:GetShardIterator",
                "dynamodb:Query",
                "dynamodb:GetItem",
                "dynamodb:Scan",
                "dynamodb:ConditionCheckItem",
                "dynamodb:BatchWriteItem",
                "dynamodb:PutItem",
                "dynamodb:UpdateItem",
                "dynamodb:DeleteItem"
              ],
              "Effect": "Allow",
              "Resource": [
                {
                  "Fn::GetAtt": [
                    "WorkflowTable",
                    "Arn"
                  ]
                },
                {
                  "Ref": "AWS::NoValue"
                }
              ]
            }
          ],
          "Version": "2012-10-17"
        },
        "PolicyName": "WorkflowIAMRoleDefaultPolicy4E30035E",
        "Roles": [
          {
            "Ref": "WorkflowIAMRole52A6C30C"
          }
        ]
      }
    },
    "DynamoDBAccess71ABE5AE": {
      "Type": "AWS::IAM::Policy",
      "Properties": {
        "PolicyDocument": {
          "Statement": [
            {
              "Action": [
                "dynamodb:BatchGetItem",
                "dynamodb:BatchWriteItem",
                "dynamodb:PutItem",
                "dynamodb:DeleteItem",
                "dynamodb:GetItem",
                "dynamodb:Scan",
                "dynamodb:Query",
                "dynamodb:UpdateItem"
              ],
              "Effect": "Allow",
              "Resource": [
                {
                  "Fn::Sub": [
                    "arn:aws:dynamodb:${AWS::Region}:${AWS::AccountId}:table/${tablename}",
                    {
                      "tablename": {
                        "Fn::Join": [
                          "",
                          [
                            "Workflow-",
                            {
                              "Ref": "referencetotransformerrootstackGraphQLAPI20497F53ApiId"
                            },
                            "-",
                            {
                              "Ref": "referencetotransformerrootstackenv10C5A902Ref"
                            }
                          ]
                        ]
                      }
                    }
                  ]
                },
                {
                  "Fn::Sub": [
                    "arn:aws:dynamodb:${AWS::Region}:${AWS::AccountId}:table/${tablename}/*",
                    {
                      "tablename": {
                        "Fn::Join": [
                          "",
                          [
                            "Workflow-",
                            {
                              "Ref": "referencetotransformerrootstackGraphQLAPI20497F53ApiId"
                            },
                            "-",
                            {
                              "Ref": "referencetotransformerrootstackenv10C5A902Ref"
                            }
                          ]
                        ]
                      }
                    }
                  ]
                }
              ]
            }
          ],
          "Version": "2012-10-17"
        },
        "PolicyName": "DynamoDBAccess71ABE5AE",
        "Roles": [
          {
            "Ref": "WorkflowIAMRole52A6C30C"
          }
        ]
      }
    },
    "WorkflowDataSource": {
      "Type": "AWS::AppSync::DataSource",
      "Properties": {
        "ApiId": {
          "Ref": "referencetotransformerrootstackGraphQLAPI20497F53ApiId"
        },
        "Name": "WorkflowTable",
        "Type": "AMAZON_DYNAMODB",
        "DynamoDBConfig": {
          "AwsRegion": {
            "Ref": "AWS::Region"
          },
          "TableName": {
            "Ref": "WorkflowTable"
          }
        },
        "ServiceRoleArn": {
          "Fn::GetAtt": [
            "WorkflowIAMRole52A6C30C",
            "Arn"
          ]
        }
      },
      "DependsOn": [
        "WorkflowIAMRole52A6C30C"
      ]
    },
    "QuerygetWorkflowpreAuth0FunctionQuerygetWorkflowpreAuth0FunctionAppSyncFunctionCFF07E03": {
      "Type": "AWS::AppSync::FunctionConfiguration",
      "Properties": {
        "ApiId": {
          "Ref": "referencetotransformerrootstackGraphQLAPI20497F53ApiId"
        },
        "DataSourceName": {
          "Ref": "referencetotransformerrootstackGraphQLAPINONEDS2BA9D1C8Name"
        },
        "FunctionVersion": "2018-05-29",
        "Name": "QuerygetWorkflowpreAuth0Function",
        "RequestMappingTemplateS3Location": {
          "Fn::Join": [
            "",
            [
              "s3://",
              {
                "Ref": "referencetotransformerrootstackS3DeploymentBucket7592718ARef"
              },
              "/",
              {
                "Ref": "referencetotransformerrootstackS3DeploymentRootKeyA71EA735Ref"
              },
              "/resolvers/Query.getWorkflow.preAuth.1.req.vtl"
            ]
          ]
        },
        "ResponseMappingTemplate": "$util.toJson({})"
      }
    },
    "QuerygetWorkflowauth0FunctionQuerygetWorkflowauth0FunctionAppSyncFunctionCEFA1C50": {
      "Type": "AWS::AppSync::FunctionConfiguration",
      "Properties": {
        "ApiId": {
          "Ref": "referencetotransformerrootstackGraphQLAPI20497F53ApiId"
        },
        "DataSourceName": {
          "Ref": "referencetotransformerrootstackGraphQLAPINONEDS2BA9D1C8Name"
        },
        "FunctionVersion": "2018-05-29",
        "Name": "QuerygetWorkflowauth0Function",
        "RequestMappingTemplateS3Location": {
          "Fn::Join": [
            "",
            [
              "s3://",
              {
                "Ref": "referencetotransformerrootstackS3DeploymentBucket7592718ARef"
              },
              "/",
              {
                "Ref": "referencetotransformerrootstackS3DeploymentRootKeyA71EA735Ref"
              },
              "/resolvers/Query.getWorkflow.auth.1.req.vtl"
            ]
          ]
        },
        "ResponseMappingTemplate": "$util.toJson({})"
      }
    },
    "QuerygetWorkflowpostAuth0FunctionQuerygetWorkflowpostAuth0FunctionAppSyncFunction6198E89E": {
      "Type": "AWS::AppSync::FunctionConfiguration",
      "Properties": {
        "ApiId": {
          "Ref": "referencetotransformerrootstackGraphQLAPI20497F53ApiId"
        },
        "DataSourceName": {
          "Ref": "referencetotransformerrootstackGraphQLAPINONEDS2BA9D1C8Name"
        },
        "FunctionVersion": "2018-05-29",
        "Name": "QuerygetWorkflowpostAuth0Function",
        "RequestMappingTemplateS3Location": {
          "Fn::Join": [
            "",
            [
              "s3://",
              {
                "Ref": "referencetotransformerrootstackS3DeploymentBucket7592718ARef"
              },
              "/",
              {
                "Ref": "referencetotransformerrootstackS3DeploymentRootKeyA71EA735Ref"
              },
              "/resolvers/Query.getWorkflow.postAuth.1.req.vtl"
            ]
          ]
        },
        "ResponseMappingTemplate": "$util.toJson({})"
      }
    },
    "QueryGetWorkflowDataResolverFnQueryGetWorkflowDataResolverFnAppSyncFunctionB3B59BB8": {
      "Type": "AWS::AppSync::FunctionConfiguration",
      "Properties": {
        "ApiId": {
          "Ref": "referencetotransformerrootstackGraphQLAPI20497F53ApiId"
        },
        "DataSourceName": {
          "Fn::GetAtt": [
            "WorkflowDataSource",
            "Name"
          ]
        },
        "FunctionVersion": "2018-05-29",
        "Name": "QueryGetWorkflowDataResolverFn",
        "RequestMappingTemplateS3Location": {
          "Fn::Join": [
            "",
            [
              "s3://",
              {
                "Ref": "referencetotransformerrootstackS3DeploymentBucket7592718ARef"
              },
              "/",
              {
                "Ref": "referencetotransformerrootstackS3DeploymentRootKeyA71EA735Ref"
              },
              "/resolvers/Query.getWorkflow.req.vtl"
            ]
          ]
        },
        "ResponseMappingTemplateS3Location": {
          "Fn::Join": [
            "",
            [
              "s3://",
              {
                "Ref": "referencetotransformerrootstackS3DeploymentBucket7592718ARef"
              },
              "/",
              {
                "Ref": "referencetotransformerrootstackS3DeploymentRootKeyA71EA735Ref"
              },
              "/resolvers/Query.getWorkflow.res.vtl"
            ]
          ]
        }
      },
      "DependsOn": [
        "WorkflowDataSource"
      ]
    },
    "GetWorkflowResolver": {
      "Type": "AWS::AppSync::Resolver",
      "Properties": {
        "ApiId": {
          "Ref": "referencetotransformerrootstackGraphQLAPI20497F53ApiId"
        },
        "FieldName": "getWorkflow",
        "TypeName": "Query",
        "Kind": "PIPELINE",
        "PipelineConfig": {
          "Functions": [
            {
              "Fn::GetAtt": [
                "QuerygetWorkflowpreAuth0FunctionQuerygetWorkflowpreAuth0FunctionAppSyncFunctionCFF07E03",
                "FunctionId"
              ]
            },
            {
              "Fn::GetAtt": [
                "QuerygetWorkflowauth0FunctionQuerygetWorkflowauth0FunctionAppSyncFunctionCEFA1C50",
                "FunctionId"
              ]
            },
            {
              "Fn::GetAtt": [
                "QuerygetWorkflowpostAuth0FunctionQuerygetWorkflowpostAuth0FunctionAppSyncFunction6198E89E",
                "FunctionId"
              ]
            },
            {
              "Fn::GetAtt": [
                "QueryGetWorkflowDataResolverFnQueryGetWorkflowDataResolverFnAppSyncFunctionB3B59BB8",
                "FunctionId"
              ]
            }
          ]
        },
        "RequestMappingTemplate": {
          "Fn::Join": [
            "",
            [
              "$util.qr($ctx.stash.put(\"typeName\", \"Query\"))\n$util.qr($ctx.stash.put(\"fieldName\", \"getWorkflow\"))\n$util.qr($ctx.stash.put(\"conditions\", []))\n$util.qr($ctx.stash.put(\"metadata\", {}))\n$util.qr($ctx.stash.metadata.put(\"dataSourceType\", \"AMAZON_DYNAMODB\"))\n$util.qr($ctx.stash.metadata.put(\"apiId\", \"",
              {
                "Ref": "referencetotransformerrootstackGraphQLAPI20497F53ApiId"
              },
              "\"))\n$util.qr($ctx.stash.put(\"tableName\", \"",
              {
                "Ref": "WorkflowTable"
              },
              "\"))\n$util.toJson({})"
            ]
          ]
        },
        "ResponseMappingTemplate": "$util.toJson($ctx.prev.result)"
      }
    },
    "QuerylistWorkflowspreAuth0FunctionQuerylistWorkflowspreAuth0FunctionAppSyncFunction59EE147A": {
      "Type": "AWS::AppSync::FunctionConfiguration",
      "Properties": {
        "ApiId": {
          "Ref": "referencetotransformerrootstackGraphQLAPI20497F53ApiId"
        },
        "DataSourceName": {
          "Ref": "referencetotransformerrootstackGraphQLAPINONEDS2BA9D1C8Name"
        },
        "FunctionVersion": "2018-05-29",
        "Name": "QuerylistWorkflowspreAuth0Function",
        "RequestMappingTemplateS3Location": {
          "Fn::Join": [
            "",
            [
              "s3://",
              {
                "Ref": "referencetotransformerrootstackS3DeploymentBucket7592718ARef"
              },
              "/",
              {
                "Ref": "referencetotransformerrootstackS3DeploymentRootKeyA71EA735Ref"
              },
              "/resolvers/Query.listWorkflows.preAuth.1.req.vtl"
            ]
          ]
        },
        "ResponseMappingTemplate": "$util.toJson({})"
      }
    },
    "QueryListWorkflowsDataResolverFnQueryListWorkflowsDataResolverFnAppSyncFunctionE91221B0": {
      "Type": "AWS::AppSync::FunctionConfiguration",
      "Properties": {
        "ApiId": {
          "Ref": "referencetotransformerrootstackGraphQLAPI20497F53ApiId"
        },
        "DataSourceName": {
          "Fn::GetAtt": [
            "WorkflowDataSource",
            "Name"
          ]
        },
        "FunctionVersion": "2018-05-29",
        "Name": "QueryListWorkflowsDataResolverFn",
        "RequestMappingTemplateS3Location": {
          "Fn::Join": [
            "",
            [
              "s3://",
              {
                "Ref": "referencetotransformerrootstackS3DeploymentBucket7592718ARef"
              },
              "/",
              {
                "Ref": "referencetotransformerrootstackS3DeploymentRootKeyA71EA735Ref"
              },
              "/resolvers/Query.listWorkflows.req.vtl"
            ]
          ]
        },
        "ResponseMappingTemplateS3Location": {
          "Fn::Join": [
            "",
            [
              "s3://",
              {
                "Ref": "referencetotransformerrootstackS3DeploymentBucket7592718ARef"
              },
              "/",
              {
                "Ref": "referencetotransformerrootstackS3DeploymentRootKeyA71EA735Ref"
              },
              "/resolvers/Query.listWorkflows.res.vtl"
            ]
          ]
        }
      },
      "DependsOn": [
        "WorkflowDataSource"
      ]
    },
    "ListWorkflowResolver": {
      "Type": "AWS::AppSync::Resolver",
      "Properties": {
        "ApiId": {
          "Ref": "referencetotransformerrootstackGraphQLAPI20497F53ApiId"
        },
        "FieldName": "listWorkflows",
        "TypeName": "Query",
        "Kind": "PIPELINE",
        "PipelineConfig": {
          "Functions": [
            {
              "Fn::GetAtt": [
                "QuerylistWorkflowspreAuth0FunctionQuerylistWorkflowspreAuth0FunctionAppSyncFunction59EE147A",
                "FunctionId"
              ]
            },
            {
              "Fn::GetAtt": [
                "QuerygetWorkflowauth0FunctionQuerygetWorkflowauth0FunctionAppSyncFunctionCEFA1C50",
                "FunctionId"
              ]
            },
            {
              "Fn::GetAtt": [
                "QuerygetWorkflowpostAuth0FunctionQuerygetWorkflowpostAuth0FunctionAppSyncFunction6198E89E",
                "FunctionId"
              ]
            },
            {
              "Fn::GetAtt": [
                "QueryListWorkflowsDataResolverFnQueryListWorkflowsDataResolverFnAppSyncFunctionE91221B0",
                "FunctionId"
              ]
            }
          ]
        },
        "RequestMappingTemplate": {
          "Fn::Join": [
            "",
            [
              "$util.qr($ctx.stash.put(\"typeName\", \"Query\"))\n$util.qr($ctx.stash.put(\"fieldName\", \"listWorkflows\"))\n$util.qr($ctx.stash.put(\"conditions\", []))\n$util.qr($ctx.stash.put(\"metadata\", {}))\n$util.qr($ctx.stash.metadata.put(\"dataSourceType\", \"AMAZON_DYNAMODB\"))\n$util.qr($ctx.stash.metadata.put(\"apiId\", \"",
              {
                "Ref": "referencetotransformerrootstackGraphQLAPI20497F53ApiId"
              },
              "\"))\n$util.qr($ctx.stash.put(\"tableName\", \"",
              {
                "Ref": "WorkflowTable"
              },
              "\"))\n$util.toJson({})"
            ]
          ]
        },
        "ResponseMappingTemplate": "$util.toJson($ctx.prev.result)"
      }
    },
    "MutationcreateWorkflowinit0FunctionMutationcreateWorkflowinit0FunctionAppSyncFunctionC34095FD": {
      "Type": "AWS::AppSync::FunctionConfiguration",
      "Properties": {
        "ApiId": {
          "Ref": "referencetotransformerrootstackGraphQLAPI20497F53ApiId"
        },
        "DataSourceName": {
          "Ref": "referencetotransformerrootstackGraphQLAPINONEDS2BA9D1C8Name"
        },
        "FunctionVersion": "2018-05-29",
        "Name": "MutationcreateWorkflowinit0Function",
        "RequestMappingTemplateS3Location": {
          "Fn::Join": [
            "",
            [
              "s3://",
              {
                "Ref": "referencetotransformerrootstackS3DeploymentBucket7592718ARef"
              },
              "/",
              {
                "Ref": "referencetotransformerrootstackS3DeploymentRootKeyA71EA735Ref"
              },
              "/resolvers/Mutation.createWorkflow.init.1.req.vtl"
            ]
          ]
        },
        "ResponseMappingTemplate": "$util.toJson({})"
      }
    },
    "MutationcreateWorkflowpreAuth0FunctionMutationcreateWorkflowpreAuth0FunctionAppSyncFunctionA1D2042B": {
      "Type": "AWS::AppSync::FunctionConfiguration",
      "Properties": {
        "ApiId": {
          "Ref": "referencetotransformerrootstackGraphQLAPI20497F53ApiId"
        },
        "DataSourceName": {
          "Ref": "referencetotransformerrootstackGraphQLAPINONEDS2BA9D1C8Name"
        },
        "FunctionVersion": "2018-05-29",
        "Name": "MutationcreateWorkflowpreAuth0Function",
        "RequestMappingTemplateS3Location": {
          "Fn::Join": [
            "",
            [
              "s3://",
              {
                "Ref": "referencetotransformerrootstackS3DeploymentBucket7592718ARef"
              },
              "/",
              {
                "Ref": "referencetotransformerrootstackS3DeploymentRootKeyA71EA735Ref"
              },
              "/resolvers/Mutation.createWorkflow.preAuth.1.req.vtl"
            ]
          ]
        },
        "ResponseMappingTemplate": "$util.toJson({})"
      }
    },
    "MutationcreateWorkflowauth0FunctionMutationcreateWorkflowauth0FunctionAppSyncFunction4203027C": {
      "Type": "AWS::AppSync::FunctionConfiguration",
      "Properties": {
        "ApiId": {
          "Ref": "referencetotransformerrootstackGraphQLAPI20497F53ApiId"
        },
        "DataSourceName": {
          "Ref": "referencetotransformerrootstackGraphQLAPINONEDS2BA9D1C8Name"
        },
        "FunctionVersion": "2018-05-29",
        "Name": "MutationcreateWorkflowauth0Function",
        "RequestMappingTemplateS3Location": {
          "Fn::Join": [
            "",
            [
              "s3://",
              {
                "Ref": "referencetotransformerrootstackS3DeploymentBucket7592718ARef"
              },
              "/",
              {
                "Ref": "referencetotransformerrootstackS3DeploymentRootKeyA71EA735Ref"
              },
              "/resolvers/Mutation.createWorkflow.auth.1.req.vtl"
            ]
          ]
        },
        "ResponseMappingTemplate": "$util.toJson({})"
      }
    },
    "MutationCreateWorkflowDataResolverFnMutationCreateWorkflowDataResolverFnAppSyncFunction4111A6CA": {
      "Type": "AWS::AppSync::FunctionConfiguration",
      "Properties": {
        "ApiId": {
          "Ref": "referencetotransformerrootstackGraphQLAPI20497F53ApiId"
        },
        "DataSourceName": {
          "Fn::GetAtt": [
            "WorkflowDataSource",
            "Name"
          ]
        },
        "FunctionVersion": "2018-05-29",
        "Name": "MutationCreateWorkflowDataResolverFn",
        "RequestMappingTemplateS3Location": {
          "Fn::Join": [
            "",
            [
              "s3://",
              {
                "Ref": "referencetotransformerrootstackS3DeploymentBucket7592718ARef"
              },
              "/",
              {
                "Ref": "referencetotransformerrootstackS3DeploymentRootKeyA71EA735Ref"
              },
              "/resolvers/Mutation.createWorkflow.req.vtl"
            ]
          ]
        },
        "ResponseMappingTemplateS3Location": {
          "Fn::Join": [
            "",
            [
              "s3://",
              {
                "Ref": "referencetotransformerrootstackS3DeploymentBucket7592718ARef"
              },
              "/",
              {
                "Ref": "referencetotransformerrootstackS3DeploymentRootKeyA71EA735Ref"
              },
              "/resolvers/Mutation.createWorkflow.res.vtl"
            ]
          ]
        }
      },
      "DependsOn": [
        "WorkflowDataSource"
      ]
    },
    "CreateWorkflowResolver": {
      "Type": "AWS::AppSync::Resolver",
      "Properties": {
        "ApiId": {
          "Ref": "referencetotransformerrootstackGraphQLAPI20497F53ApiId"
        },
        "FieldName": "createWorkflow",
        "TypeName": "Mutation",
        "Kind": "PIPELINE",
        "PipelineConfig": {
          "Functions": [
            {
              "Fn::GetAtt": [
                "MutationcreateWorkflowinit0FunctionMutationcreateWorkflowinit0FunctionAppSyncFunctionC34095FD",
                "FunctionId"
              ]
            },
            {
              "Fn::GetAtt": [
                "MutationcreateWorkflowpreAuth0FunctionMutationcreateWorkflowpreAuth0FunctionAppSyncFunctionA1D2042B",
                "FunctionId"
              ]
            },
            {
              "Fn::GetAtt": [
                "MutationcreateWorkflowauth0FunctionMutationcreateWorkflowauth0FunctionAppSyncFunction4203027C",
                "FunctionId"
              ]
            },
            {
              "Fn::GetAtt": [
                "QuerygetWorkflowpostAuth0FunctionQuerygetWorkflowpostAuth0FunctionAppSyncFunction6198E89E",
                "FunctionId"
              ]
            },
            {
              "Fn::GetAtt": [
                "MutationCreateWorkflowDataResolverFnMutationCreateWorkflowDataResolverFnAppSyncFunction4111A6CA",
                "FunctionId"
              ]
            }
          ]
        },
        "RequestMappingTemplate": {
          "Fn::Join": [
            "",
            [
              "$util.qr($ctx.stash.put(\"typeName\", \"Mutation\"))\n$util.qr($ctx.stash.put(\"fieldName\", \"createWorkflow\"))\n$util.qr($ctx.stash.put(\"conditions\", []))\n$util.qr($ctx.stash.put(\"metadata\", {}))\n$util.qr($ctx.stash.metadata.put(\"dataSourceType\", \"AMAZON_DYNAMODB\"))\n$util.qr($ctx.stash.metadata.put(\"apiId\", \"",
              {
                "Ref": "referencetotransformerrootstackGraphQLAPI20497F53ApiId"
              },
              "\"))\n$util.qr($ctx.stash.put(\"tableName\", \"",
              {
                "Ref": "WorkflowTable"
              },
              "\"))\n$util.toJson({})"
            ]
          ]
        },
        "ResponseMappingTemplate": "$util.toJson($ctx.prev.result)"
      }
    },
    "MutationupdateWorkflowinit0FunctionMutationupdateWorkflowinit0FunctionAppSyncFunctionB05F1098": {
      "Type": "AWS::AppSync::FunctionConfiguration",
      "Properties": {
        "ApiId": {
          "Ref": "referencetotransformerrootstackGraphQLAPI20497F53ApiId"
        },
        "DataSourceName": {
          "Ref": "referencetotransformerrootstackGraphQLAPINONEDS2BA9D1C8Name"
        },
        "FunctionVersion": "2018-05-29",
        "Name": "MutationupdateWorkflowinit0Function",
        "RequestMappingTemplateS3Location": {
          "Fn::Join": [
            "",
            [
              "s3://",
              {
                "Ref": "referencetotransformerrootstackS3DeploymentBucket7592718ARef"
              },
              "/",
              {
                "Ref": "referencetotransformerrootstackS3DeploymentRootKeyA71EA735Ref"
              },
              "/resolvers/Mutation.updateWorkflow.init.1.req.vtl"
            ]
          ]
        },
        "ResponseMappingTemplate": "$util.toJson({})"
      }
    },
    "MutationupdateWorkflowauth0FunctionMutationupdateWorkflowauth0FunctionAppSyncFunction5F362D45": {
      "Type": "AWS::AppSync::FunctionConfiguration",
      "Properties": {
        "ApiId": {
          "Ref": "referencetotransformerrootstackGraphQLAPI20497F53ApiId"
        },
        "DataSourceName": {
          "Fn::GetAtt": [
            "WorkflowDataSource",
            "Name"
          ]
        },
        "FunctionVersion": "2018-05-29",
        "Name": "MutationupdateWorkflowauth0Function",
        "RequestMappingTemplateS3Location": {
          "Fn::Join": [
            "",
            [
              "s3://",
              {
                "Ref": "referencetotransformerrootstackS3DeploymentBucket7592718ARef"
              },
              "/",
              {
                "Ref": "referencetotransformerrootstackS3DeploymentRootKeyA71EA735Ref"
              },
              "/resolvers/Mutation.updateWorkflow.auth.1.req.vtl"
            ]
          ]
        },
        "ResponseMappingTemplateS3Location": {
          "Fn::Join": [
            "",
            [
              "s3://",
              {
                "Ref": "referencetotransformerrootstackS3DeploymentBucket7592718ARef"
              },
              "/",
              {
                "Ref": "referencetotransformerrootstackS3DeploymentRootKeyA71EA735Ref"
              },
              "/resolvers/Mutation.updateWorkflow.auth.1.res.vtl"
            ]
          ]
        }
      },
      "DependsOn": [
        "WorkflowDataSource"
      ]
    },
    "MutationUpdateWorkflowDataResolverFnMutationUpdateWorkflowDataResolverFnAppSyncFunction699C4DC9": {
      "Type": "AWS::AppSync::FunctionConfiguration",
      "Properties": {
        "ApiId": {
          "Ref": "referencetotransformerrootstackGraphQLAPI20497F53ApiId"
        },
        "DataSourceName": {
          "Fn::GetAtt": [
            "WorkflowDataSource",
            "Name"
          ]
        },
        "FunctionVersion": "2018-05-29",
        "Name": "MutationUpdateWorkflowDataResolverFn",
        "RequestMappingTemplateS3Location": {
          "Fn::Join": [
            "",
            [
              "s3://",
              {
                "Ref": "referencetotransformerrootstackS3DeploymentBucket7592718ARef"
              },
              "/",
              {
                "Ref": "referencetotransformerrootstackS3DeploymentRootKeyA71EA735Ref"
              },
              "/resolvers/Mutation.updateWorkflow.req.vtl"
            ]
          ]
        },
        "ResponseMappingTemplateS3Location": {
          "Fn::Join": [
            "",
            [
              "s3://",
              {
                "Ref": "referencetotransformerrootstackS3DeploymentBucket7592718ARef"
              },
              "/",
              {
                "Ref": "referencetotransformerrootstackS3DeploymentRootKeyA71EA735Ref"
              },
              "/resolvers/Mutation.updateWorkflow.res.vtl"
            ]
          ]
        }
      },
      "DependsOn": [
        "WorkflowDataSource"
      ]
    },
    "UpdateWorkflowResolver": {
      "Type": "AWS::AppSync::Resolver",
      "Properties": {
        "ApiId": {
          "Ref": "referencetotransformerrootstackGraphQLAPI20497F53ApiId"
        },
        "FieldName": "updateWorkflow",
        "TypeName": "Mutation",
        "Kind": "PIPELINE",
        "PipelineConfig": {
          "Functions": [
            {
              "Fn::GetAtt": [
                "MutationupdateWorkflowinit0FunctionMutationupdateWorkflowinit0FunctionAppSyncFunctionB05F1098",
                "FunctionId"
              ]
            },
            {
              "Fn::GetAtt": [
                "MutationcreateWorkflowpreAuth0FunctionMutationcreateWorkflowpreAuth0FunctionAppSyncFunctionA1D2042B",
                "FunctionId"
              ]
            },
            {
              "Fn::GetAtt": [
                "MutationupdateWorkflowauth0FunctionMutationupdateWorkflowauth0FunctionAppSyncFunction5F362D45",
                "FunctionId"
              ]
            },
            {
              "Fn::GetAtt": [
                "QuerygetWorkflowpostAuth0FunctionQuerygetWorkflowpostAuth0FunctionAppSyncFunction6198E89E",
                "FunctionId"
              ]
            },
            {
              "Fn::GetAtt": [
                "MutationUpdateWorkflowDataResolverFnMutationUpdateWorkflowDataResolverFnAppSyncFunction699C4DC9",
                "FunctionId"
              ]
            }
          ]
        },
        "RequestMappingTemplate": {
          "Fn::Join": [
            "",
            [
              "$util.qr($ctx.stash.put(\"typeName\", \"Mutation\"))\n$util.qr($ctx.stash.put(\"fieldName\", \"updateWorkflow\"))\n$util.qr($ctx.stash.put(\"conditions\", []))\n$util.qr($ctx.stash.put(\"metadata\", {}))\n$util.qr($ctx.stash.metadata.put(\"dataSourceType\", \"AMAZON_DYNAMODB\"))\n$util.qr($ctx.stash.metadata.put(\"apiId\", \"",
              {
                "Ref": "referencetotransformerrootstackGraphQLAPI20497F53ApiId"
              },
              "\"))\n$util.qr($ctx.stash.put(\"tableName\", \"",
              {
                "Ref": "WorkflowTable"
              },
              "\"))\n$util.toJson({})"
            ]
          ]
        },
        "ResponseMappingTemplate": "$util.toJson($ctx.prev.result)"
      }
    },
    "MutationdeleteWorkflowpreAuth0FunctionMutationdeleteWorkflowpreAuth0FunctionAppSyncFunction1C1B151D": {
      "Type": "AWS::AppSync::FunctionConfiguration",
      "Properties": {
        "ApiId": {
          "Ref": "referencetotransformerrootstackGraphQLAPI20497F53ApiId"
        },
        "DataSourceName": {
          "Ref": "referencetotransformerrootstackGraphQLAPINONEDS2BA9D1C8Name"
        },
        "FunctionVersion": "2018-05-29",
        "Name": "MutationdeleteWorkflowpreAuth0Function",
        "RequestMappingTemplateS3Location": {
          "Fn::Join": [
            "",
            [
              "s3://",
              {
                "Ref": "referencetotransformerrootstackS3DeploymentBucket7592718ARef"
              },
              "/",
              {
                "Ref": "referencetotransformerrootstackS3DeploymentRootKeyA71EA735Ref"
              },
              "/resolvers/Mutation.deleteWorkflow.preAuth.1.req.vtl"
            ]
          ]
        },
        "ResponseMappingTemplate": "$util.toJson({})"
      }
    },
    "MutationdeleteWorkflowauth0FunctionMutationdeleteWorkflowauth0FunctionAppSyncFunction841C6606": {
      "Type": "AWS::AppSync::FunctionConfiguration",
      "Properties": {
        "ApiId": {
          "Ref": "referencetotransformerrootstackGraphQLAPI20497F53ApiId"
        },
        "DataSourceName": {
          "Fn::GetAtt": [
            "WorkflowDataSource",
            "Name"
          ]
        },
        "FunctionVersion": "2018-05-29",
        "Name": "MutationdeleteWorkflowauth0Function",
        "RequestMappingTemplateS3Location": {
          "Fn::Join": [
            "",
            [
              "s3://",
              {
                "Ref": "referencetotransformerrootstackS3DeploymentBucket7592718ARef"
              },
              "/",
              {
                "Ref": "referencetotransformerrootstackS3DeploymentRootKeyA71EA735Ref"
              },
              "/resolvers/Mutation.deleteWorkflow.auth.1.req.vtl"
            ]
          ]
        },
        "ResponseMappingTemplateS3Location": {
          "Fn::Join": [
            "",
            [
              "s3://",
              {
                "Ref": "referencetotransformerrootstackS3DeploymentBucket7592718ARef"
              },
              "/",
              {
                "Ref": "referencetotransformerrootstackS3DeploymentRootKeyA71EA735Ref"
              },
              "/resolvers/Mutation.deleteWorkflow.auth.1.res.vtl"
            ]
          ]
        }
      },
      "DependsOn": [
        "WorkflowDataSource"
      ]
    },
    "MutationDeleteWorkflowDataResolverFnMutationDeleteWorkflowDataResolverFnAppSyncFunction2E99DC49": {
      "Type": "AWS::AppSync::FunctionConfiguration",
      "Properties": {
        "ApiId": {
          "Ref": "referencetotransformerrootstackGraphQLAPI20497F53ApiId"
        },
        "DataSourceName": {
          "Fn::GetAtt": [
            "WorkflowDataSource",
            "Name"
          ]
        },
        "FunctionVersion": "2018-05-29",
        "Name": "MutationDeleteWorkflowDataResolverFn",
        "RequestMappingTemplateS3Location": {
          "Fn::Join": [
            "",
            [
              "s3://",
              {
                "Ref": "referencetotransformerrootstackS3DeploymentBucket7592718ARef"
              },
              "/",
              {
                "Ref": "referencetotransformerrootstackS3DeploymentRootKeyA71EA735Ref"
              },
              "/resolvers/Mutation.deleteWorkflow.req.vtl"
            ]
          ]
        },
        "ResponseMappingTemplateS3Location": {
          "Fn::Join": [
            "",
            [
              "s3://",
              {
                "Ref": "referencetotransformerrootstackS3DeploymentBucket7592718ARef"
              },
              "/",
              {
                "Ref": "referencetotransformerrootstackS3DeploymentRootKeyA71EA735Ref"
              },
              "/resolvers/Mutation.deleteWorkflow.res.vtl"
            ]
          ]
        }
      },
      "DependsOn": [
        "WorkflowDataSource"
      ]
    },
    "DeleteWorkflowResolver": {
      "Type": "AWS::AppSync::Resolver",
      "Properties": {
        "ApiId": {
          "Ref": "referencetotransformerrootstackGraphQLAPI20497F53ApiId"
        },
        "FieldName": "deleteWorkflow",
        "TypeName": "Mutation",
        "Kind": "PIPELINE",
        "PipelineConfig": {
          "Functions": [
            {
              "Fn::GetAtt": [
                "MutationdeleteWorkflowpreAuth0FunctionMutationdeleteWorkflowpreAuth0FunctionAppSyncFunction1C1B151D",
                "FunctionId"
              ]
            },
            {
              "Fn::GetAtt": [
                "MutationdeleteWorkflowauth0FunctionMutationdeleteWorkflowauth0FunctionAppSyncFunction841C6606",
                "FunctionId"
              ]
            },
            {
              "Fn::GetAtt": [
                "QuerygetWorkflowpostAuth0FunctionQuerygetWorkflowpostAuth0FunctionAppSyncFunction6198E89E",
                "FunctionId"
              ]
            },
            {
              "Fn::GetAtt": [
                "MutationDeleteWorkflowDataResolverFnMutationDeleteWorkflowDataResolverFnAppSyncFunction2E99DC49",
                "FunctionId"
              ]
            }
          ]
        },
        "RequestMappingTemplate": {
          "Fn::Join": [
            "",
            [
              "$util.qr($ctx.stash.put(\"typeName\", \"Mutation\"))\n$util.qr($ctx.stash.put(\"fieldName\", \"deleteWorkflow\"))\n$util.qr($ctx.stash.put(\"conditions\", []))\n$util.qr($ctx.stash.put(\"metadata\", {}))\n$util.qr($ctx.stash.metadata.put(\"dataSourceType\", \"AMAZON_DYNAMODB\"))\n$util.qr($ctx.stash.metadata.put(\"apiId\", \"",
              {
                "Ref": "referencetotransformerrootstackGraphQLAPI20497F53ApiId"
              },
              "\"))\n$util.qr($ctx.stash.put(\"tableName\", \"",
              {
                "Ref": "WorkflowTable"
              },
              "\"))\n$util.toJson({})"
            ]
          ]
        },
        "ResponseMappingTemplate": "$util.toJson($ctx.prev.result)"
      }
    },
    "SubscriptiononCreateWorkflowauth0FunctionSubscriptiononCreateWorkflowauth0FunctionAppSyncFunctionE8741645": {
      "Type": "AWS::AppSync::FunctionConfiguration",
      "Properties": {
        "ApiId": {
          "Ref": "referencetotransformerrootstackGraphQLAPI20497F53ApiId"
        },
        "DataSourceName": {
          "Ref": "referencetotransformerrootstackGraphQLAPINONEDS2BA9D1C8Name"
        },
        "FunctionVersion": "2018-05-29",
        "Name": "SubscriptiononCreateWorkflowauth0Function",
        "RequestMappingTemplateS3Location": {
          "Fn::Join": [
            "",
            [
              "s3://",
              {
                "Ref": "referencetotransformerrootstackS3DeploymentBucket7592718ARef"
              },
              "/",
              {
                "Ref": "referencetotransformerrootstackS3DeploymentRootKeyA71EA735Ref"
              },
              "/resolvers/Subscription.onCreateWorkflow.auth.1.req.vtl"
            ]
          ]
        },
        "ResponseMappingTemplate": "$util.toJson({})"
      }
    },
    "SubscriptionOnCreateWorkflowDataResolverFnSubscriptionOnCreateWorkflowDataResolverFnAppSyncFunction66D3AA65": {
      "Type": "AWS::AppSync::FunctionConfiguration",
      "Properties": {
        "ApiId": {
          "Ref": "referencetotransformerrootstackGraphQLAPI20497F53ApiId"
        },
        "DataSourceName": {
          "Ref": "referencetotransformerrootstackGraphQLAPINONEDS2BA9D1C8Name"
        },
        "FunctionVersion": "2018-05-29",
        "Name": "SubscriptionOnCreateWorkflowDataResolverFn",
        "RequestMappingTemplateS3Location": {
          "Fn::Join": [
            "",
            [
              "s3://",
              {
                "Ref": "referencetotransformerrootstackS3DeploymentBucket7592718ARef"
              },
              "/",
              {
                "Ref": "referencetotransformerrootstackS3DeploymentRootKeyA71EA735Ref"
              },
              "/resolvers/Subscription.onCreateWorkflow.req.vtl"
            ]
          ]
        },
        "ResponseMappingTemplateS3Location": {
          "Fn::Join": [
            "",
            [
              "s3://",
              {
                "Ref": "referencetotransformerrootstackS3DeploymentBucket7592718ARef"
              },
              "/",
              {
                "Ref": "referencetotransformerrootstackS3DeploymentRootKeyA71EA735Ref"
              },
              "/resolvers/Subscription.onCreateWorkflow.res.vtl"
            ]
          ]
        }
      }
    },
    "SubscriptiononCreateWorkflowResolver": {
      "Type": "AWS::AppSync::Resolver",
      "Properties": {
        "ApiId": {
          "Ref": "referencetotransformerrootstackGraphQLAPI20497F53ApiId"
        },
        "FieldName": "onCreateWorkflow",
        "TypeName": "Subscription",
        "Kind": "PIPELINE",
        "PipelineConfig": {
          "Functions": [
            {
              "Fn::GetAtt": [
                "SubscriptiononCreateWorkflowauth0FunctionSubscriptiononCreateWorkflowauth0FunctionAppSyncFunctionE8741645",
                "FunctionId"
              ]
            },
            {
              "Fn::GetAtt": [
                "QuerygetWorkflowpostAuth0FunctionQuerygetWorkflowpostAuth0FunctionAppSyncFunction6198E89E",
                "FunctionId"
              ]
            },
            {
              "Fn::GetAtt": [
                "SubscriptionOnCreateWorkflowDataResolverFnSubscriptionOnCreateWorkflowDataResolverFnAppSyncFunction66D3AA65",
                "FunctionId"
              ]
            }
          ]
        },
        "RequestMappingTemplate": {
          "Fn::Join": [
            "",
            [
              "$util.qr($ctx.stash.put(\"typeName\", \"Subscription\"))\n$util.qr($ctx.stash.put(\"fieldName\", \"onCreateWorkflow\"))\n$util.qr($ctx.stash.put(\"conditions\", []))\n$util.qr($ctx.stash.put(\"metadata\", {}))\n$util.qr($ctx.stash.metadata.put(\"dataSourceType\", \"NONE\"))\n$util.qr($ctx.stash.metadata.put(\"apiId\", \"",
              {
                "Ref": "referencetotransformerrootstackGraphQLAPI20497F53ApiId"
              },
              "\"))\n\n$util.toJson({})"
            ]
          ]
        },
        "ResponseMappingTemplate": "$util.toJson($ctx.prev.result)"
      }
    },
    "SubscriptiononUpdateWorkflowResolver": {
      "Type": "AWS::AppSync::Resolver",
      "Properties": {
        "ApiId": {
          "Ref": "referencetotransformerrootstackGraphQLAPI20497F53ApiId"
        },
        "FieldName": "onUpdateWorkflow",
        "TypeName": "Subscription",
        "Kind": "PIPELINE",
        "PipelineConfig": {
          "Functions": [
            {
              "Fn::GetAtt": [
                "SubscriptiononCreateWorkflowauth0FunctionSubscriptiononCreateWorkflowauth0FunctionAppSyncFunctionE8741645",
                "FunctionId"
              ]
            },
            {
              "Fn::GetAtt": [
                "QuerygetWorkflowpostAuth0FunctionQuerygetWorkflowpostAuth0FunctionAppSyncFunction6198E89E",
                "FunctionId"
              ]
            },
            {
              "Fn::GetAtt": [
                "SubscriptionOnCreateWorkflowDataResolverFnSubscriptionOnCreateWorkflowDataResolverFnAppSyncFunction66D3AA65",
                "FunctionId"
              ]
            }
          ]
        },
        "RequestMappingTemplate": {
          "Fn::Join": [
            "",
            [
              "$util.qr($ctx.stash.put(\"typeName\", \"Subscription\"))\n$util.qr($ctx.stash.put(\"fieldName\", \"onUpdateWorkflow\"))\n$util.qr($ctx.stash.put(\"conditions\", []))\n$util.qr($ctx.stash.put(\"metadata\", {}))\n$util.qr($ctx.stash.metadata.put(\"dataSourceType\", \"NONE\"))\n$util.qr($ctx.stash.metadata.put(\"apiId\", \"",
              {
                "Ref": "referencetotransformerrootstackGraphQLAPI20497F53ApiId"
              },
              "\"))\n\n$util.toJson({})"
            ]
          ]
        },
        "ResponseMappingTemplate": "$util.toJson($ctx.prev.result)"
      }
    },
    "SubscriptiononDeleteWorkflowResolver": {
      "Type": "AWS::AppSync::Resolver",
      "Properties": {
        "ApiId": {
          "Ref": "referencetotransformerrootstackGraphQLAPI20497F53ApiId"
        },
        "FieldName": "onDeleteWorkflow",
        "TypeName": "Subscription",
        "Kind": "PIPELINE",
        "PipelineConfig": {
          "Functions": [
            {
              "Fn::GetAtt": [
                "SubscriptiononCreateWorkflowauth0FunctionSubscriptiononCreateWorkflowauth0FunctionAppSyncFunctionE8741645",
                "FunctionId"
              ]
            },
            {
              "Fn::GetAtt": [
                "QuerygetWorkflowpostAuth0FunctionQuerygetWorkflowpostAuth0FunctionAppSyncFunction6198E89E",
                "FunctionId"
              ]
            },
            {
              "Fn::GetAtt": [
                "SubscriptionOnCreateWorkflowDataResolverFnSubscriptionOnCreateWorkflowDataResolverFnAppSyncFunction66D3AA65",
                "FunctionId"
              ]
            }
          ]
        },
        "RequestMappingTemplate": {
          "Fn::Join": [
            "",
            [
              "$util.qr($ctx.stash.put(\"typeName\", \"Subscription\"))\n$util.qr($ctx.stash.put(\"fieldName\", \"onDeleteWorkflow\"))\n$util.qr($ctx.stash.put(\"conditions\", []))\n$util.qr($ctx.stash.put(\"metadata\", {}))\n$util.qr($ctx.stash.metadata.put(\"dataSourceType\", \"NONE\"))\n$util.qr($ctx.stash.metadata.put(\"apiId\", \"",
              {
                "Ref": "referencetotransformerrootstackGraphQLAPI20497F53ApiId"
              },
              "\"))\n\n$util.toJson({})"
            ]
          ]
        },
        "ResponseMappingTemplate": "$util.toJson($ctx.prev.result)"
      }
    }
  },
  "Outputs": {
    "GetAttWorkflowTableStreamArn": {
      "Description": "Your DynamoDB table StreamArn.",
      "Value": {
        "Fn::GetAtt": [
          "WorkflowTable",
          "StreamArn"
        ]
      },
      "Export": {
        "Name": {
          "Fn::Join": [
            ":",
            [
              {
                "Ref": "referencetotransformerrootstackGraphQLAPI20497F53ApiId"
              },
              "GetAtt:WorkflowTable:StreamArn"
            ]
          ]
        }
      }
    },
    "GetAttWorkflowTableName": {
      "Description": "Your DynamoDB table name.",
      "Value": {
        "Ref": "WorkflowTable"
      },
      "Export": {
        "Name": {
          "Fn::Join": [
            ":",
            [
              {
                "Ref": "referencetotransformerrootstackGraphQLAPI20497F53ApiId"
              },
              "GetAtt:WorkflowTable:Name"
            ]
          ]
        }
      }
    },
    "GetAttWorkflowDataSourceName": {
      "Description": "Your model DataSource name.",
      "Value": {
        "Fn::GetAtt": [
          "WorkflowDataSource",
          "Name"
        ]
      },
      "Export": {
        "Name": {
          "Fn::Join": [
            ":",
            [
              {
                "Ref": "referencetotransformerrootstackGraphQLAPI20497F53ApiId"
              },
              "GetAtt:WorkflowDataSource:Name"
            ]
          ]
        }
      }
    },
    "transformerrootstackWorkflowQuerygetWorkflowauth0FunctionQuerygetWorkflowauth0FunctionAppSyncFunction363A84A3FunctionId": {
      "Value": {
        "Fn::GetAtt": [
          "QuerygetWorkflowauth0FunctionQuerygetWorkflowauth0FunctionAppSyncFunctionCEFA1C50",
          "FunctionId"
        ]
      }
    },
    "transformerrootstackWorkflowQuerygetWorkflowpostAuth0FunctionQuerygetWorkflowpostAuth0FunctionAppSyncFunction525087F5FunctionId": {
      "Value": {
        "Fn::GetAtt": [
          "QuerygetWorkflowpostAuth0FunctionQuerygetWorkflowpostAuth0FunctionAppSyncFunction6198E89E",
          "FunctionId"
        ]
      }
    },
    "transformerrootstackWorkflowMutationcreateWorkflowinit0FunctionMutationcreateWorkflowinit0FunctionAppSyncFunctionA74B7521FunctionId": {
      "Value": {
        "Fn::GetAtt": [
          "MutationcreateWorkflowinit0FunctionMutationcreateWorkflowinit0FunctionAppSyncFunctionC34095FD",
          "FunctionId"
        ]
      }
    },
    "transformerrootstackWorkflowMutationcreateWorkflowauth0FunctionMutationcreateWorkflowauth0FunctionAppSyncFunction48836C0BFunctionId": {
      "Value": {
        "Fn::GetAtt": [
          "MutationcreateWorkflowauth0FunctionMutationcreateWorkflowauth0FunctionAppSyncFunction4203027C",
          "FunctionId"
        ]
      }
    },
    "transformerrootstackWorkflowMutationupdateWorkflowinit0FunctionMutationupdateWorkflowinit0FunctionAppSyncFunction9440F930FunctionId": {
      "Value": {
        "Fn::GetAtt": [
          "MutationupdateWorkflowinit0FunctionMutationupdateWorkflowinit0FunctionAppSyncFunctionB05F1098",
          "FunctionId"
        ]
      }
    },
    "transformerrootstackWorkflowSubscriptiononCreateWorkflowauth0FunctionSubscriptiononCreateWorkflowauth0FunctionAppSyncFunctionEE77C9A3FunctionId": {
      "Value": {
        "Fn::GetAtt": [
          "SubscriptiononCreateWorkflowauth0FunctionSubscriptiononCreateWorkflowauth0FunctionAppSyncFunctionE8741645",
          "FunctionId"
        ]
      }
    },
    "transformerrootstackWorkflowSubscriptionOnCreateWorkflowDataResolverFnSubscriptionOnCreateWorkflowDataResolverFnAppSyncFunctionD6E0A813FunctionId": {
      "Value": {
        "Fn::GetAtt": [
          "SubscriptionOnCreateWorkflowDataResolverFnSubscriptionOnCreateWorkflowDataResolverFnAppSyncFunction66D3AA65",
          "FunctionId"
        ]
      }
    }
  }
}